guirecognizerapp/__builtins__.pyi
guirecognizerapp/__init__.py
guirecognizerapp/__main__.py
guirecognizerapp/action_manager.py
guirecognizerapp/cache_manager.py
guirecognizerapp/call_manager.py
guirecognizerapp/file_manager.py
guirecognizerapp/main.py
guirecognizerapp/process_manager.py
guirecognizerapp/screen_helper.py
guirecognizerapp/screenshot_manager.py
guirecognizerapp/server.py
guirecognizerapp/server_client_interface.py
guirecognizerapp/settings_manager.py
guirecognizerapp/generated/client/index.html
guirecognizerapp/generated/client/site.webmanifest
guirecognizerapp/generated/client/assets/index-Bi1pQWyf.css
guirecognizerapp/generated/client/assets/index-CjM2VLJ_.js
guirecognizerapp/generated/client/favicon/android-chrome-192x192.png
guirecognizerapp/generated/client/favicon/android-chrome-512x512.png
guirecognizerapp/generated/client/favicon/apple-touch-icon.png
guirecognizerapp/generated/client/favicon/favicon-16x16.png
guirecognizerapp/generated/client/favicon/favicon-32x32.png
guirecognizerapp/generated/client/favicon/favicon.ico
guirecognizerapp/locale/en/LC_MESSAGES/base.mo
guirecognizerapp/resources/favicon.ico
guirecognizerapp-0.1.1.dist-info/licenses/LICENSE
guirecognizerapp-0.1.1.dist-info/METADATA
guirecognizerapp-0.1.1.dist-info/WHEEL
guirecognizerapp-0.1.1.dist-info/top_level.txt
guirecognizerapp-0.1.1.dist-info/RECORD
