Metadata-Version: 2.4
Name: guirecognizerapp
Version: 0.1.1
Summary: Companion application for library guirecognizer
Author-email: FAB V <fab5code@gmail.com>
License-Expression: MIT
Project-URL: Repository, https://github.com/fab5code/guirecognizerapp.git
Project-URL: Issues, https://github.com/fab5code/guirecognizerapp/issues
Keywords: GUI,recognize,screen
Classifier: Development Status :: 3 - Alpha
Classifier: Intended Audience :: Developers
Classifier: Programming Language :: Python :: 3.13
Requires-Python: >=3.13
License-File: LICENSE
Requires-Dist: guirecognizer
Requires-Dist: fastapi[standard]<0.117.0,>=0.116.1
Requires-Dist: keyboard
Requires-Dist: platformdirs
Requires-Dist: show-in-file-manager
Requires-Dist: screeninfo; sys_platform == "win32"
Provides-Extra: dev
Requires-Dist: packaging; extra == "dev"
Requires-Dist: coverage; extra == "dev"
Requires-Dist: build; extra == "dev"
Requires-Dist: twine; extra == "dev"
Requires-Dist: pytesseract; extra == "dev"
Requires-Dist: easyocr; extra == "dev"
Requires-Dist: Babel; extra == "dev"
Dynamic: license-file
